dynasty_dl/__init__.py
dynasty_dl/__main__.py
dynasty_dl/dynasty.py
dynasty_dl-0.1.0.dist-info/LICENSE
dynasty_dl-0.1.0.dist-info/WHEEL
dynasty_dl-0.1.0.dist-info/entry_points.txt
dynasty_dl-0.1.0.dist-info/METADATA
dynasty_dl-0.1.0.dist-info/RECORD
